docs/assets/logo.svg
examples/bc.py
examples/collect_offline_data.py
examples/network.py
examples/ppo_with_reg.py
mahjax/__init__.py
mahjax/core.py
mahjax/_src/__init__.py
mahjax/_src/struct.py
mahjax/_src/types.py
mahjax/_src/visualizer.py
mahjax/_src/dwg/__init__.py
mahjax/_src/dwg/mahjong_tile.py
mahjax/_src/dwg/mahjong_visualizer.py
mahjax/no_red_mahjong/action.py
mahjax/no_red_mahjong/env.py
mahjax/no_red_mahjong/hand.py
mahjax/no_red_mahjong/meld.py
mahjax/no_red_mahjong/players.py
mahjax/no_red_mahjong/shanten.py
mahjax/no_red_mahjong/state.py
mahjax/no_red_mahjong/tile.py
mahjax/no_red_mahjong/yaku.py
mahjax/no_red_mahjong/cache/hand_cache.npz
mahjax/no_red_mahjong/cache/shanten_cache.npz
mahjax/no_red_mahjong/cache/yaku_cache.npz
mahjax/ui/__init__.py
mahjax/ui/agents.py
mahjax/ui/app.py
mahjax/ui/game_manager.py
mahjax/ui/utils.py
mahjax/wrappers/__init__.py
mahjax/wrappers/auto_reset_wrapper.py
tests/__init__.py
tests/no_red_mahjong/__init__.py
tests/no_red_mahjong/test_env.py
tests/no_red_mahjong/test_hand.py
tests/no_red_mahjong/test_meld.py
tests/no_red_mahjong/test_observe.py
tests/no_red_mahjong/test_play.py
tests/no_red_mahjong/test_shanten.py
tests/no_red_mahjong/test_special_case.py
tests/no_red_mahjong/test_tile.py
tests/no_red_mahjong/test_visualize.py
tests/no_red_mahjong/test_yaku.py
workspace/random.svg
workspace/svg2gif.py
mahjax-0.0.1.dist-info/METADATA
mahjax-0.0.1.dist-info/WHEEL
mahjax-0.0.1.dist-info/top_level.txt
mahjax-0.0.1.dist-info/RECORD
