Metadata-Version: 2.4
Name: mahjax
Version: 0.0.1
Summary: GPU-accelerated vectorized mahjong simulators for reinforcement learning
Author: Soichiro Nishimori
Author-email: Soichiro Nishimori <gatikiti.630@gmail.com>
License: Apache-2.0
Project-URL: Source, https://github.com/nissymori/mahjax
Classifier: Programming Language :: Python :: 3.9
Classifier: Programming Language :: Python :: 3.10
Classifier: Programming Language :: Python :: 3.11
Classifier: Programming Language :: Python :: 3.12
Classifier: Programming Language :: Python :: 3.13
Requires-Python: >=3.9
Requires-Dist: jax>=0.4.28
Requires-Dist: typing_extensions>=4.2.0
Requires-Dist: svgwrite
Requires-Dist: fastapi
Requires-Dist: uvicorn
Dynamic: author
